wizdiff/__init__.py
wizdiff/db.py
wizdiff/delta.py
wizdiff/dml_parser.py
wizdiff/update_notifier.py
wizdiff/utils.py
wizdiff/webdriver.py
wizdiff-0.2.1.dist-info/LICENSE
wizdiff-0.2.1.dist-info/WHEEL
wizdiff-0.2.1.dist-info/METADATA
wizdiff-0.2.1.dist-info/RECORD
