Metadata-Version: 2.1
Name: wizdiff
Version: 0.2.1
Summary: wizard101 version diffing automation tool
Author: StarrFox
Author-email: starrfox6312@gmail.com
Requires-Python: >=3.8,<4.0
Classifier: Programming Language :: Python :: 3
Classifier: Programming Language :: Python :: 3.10
Classifier: Programming Language :: Python :: 3.8
Classifier: Programming Language :: Python :: 3.9
Requires-Dist: aiohttp (>=3.8.1,<4.0.0)
Requires-Dist: aiosqlite (>=0.17.0,<0.18.0)
Requires-Dist: click (>=8.0.1,<9.0.0)
Requires-Dist: loguru (>=0.6.0,<0.7.0)
